gooddata_sdk/__init__.py
gooddata_sdk/_version.py
gooddata_sdk/client.py
gooddata_sdk/config.py
gooddata_sdk/py.typed
gooddata_sdk/sdk.py
gooddata_sdk/support.py
gooddata_sdk/table.py
gooddata_sdk/type_converter.py
gooddata_sdk/utils.py
gooddata_sdk/visualization.py
gooddata_sdk/catalog/__init__.py
gooddata_sdk/catalog/base.py
gooddata_sdk/catalog/catalog_service_base.py
gooddata_sdk/catalog/depends_on.py
gooddata_sdk/catalog/entity.py
gooddata_sdk/catalog/filter_by.py
gooddata_sdk/catalog/identifier.py
gooddata_sdk/catalog/parameter.py
gooddata_sdk/catalog/rule.py
gooddata_sdk/catalog/setting.py
gooddata_sdk/catalog/types.py
gooddata_sdk/catalog/validate_by_item.py
gooddata_sdk/catalog/data_source/__init__.py
gooddata_sdk/catalog/data_source/service.py
gooddata_sdk/catalog/data_source/action_model/__init__.py
gooddata_sdk/catalog/data_source/action_model/sql_column.py
gooddata_sdk/catalog/data_source/action_model/requests/__init__.py
gooddata_sdk/catalog/data_source/action_model/requests/ldm_request.py
gooddata_sdk/catalog/data_source/action_model/requests/scan_model_request.py
gooddata_sdk/catalog/data_source/action_model/requests/scan_sql_request.py
gooddata_sdk/catalog/data_source/action_model/responses/__init__.py
gooddata_sdk/catalog/data_source/action_model/responses/scan_sql_response.py
gooddata_sdk/catalog/data_source/declarative_model/__init__.py
gooddata_sdk/catalog/data_source/declarative_model/data_source.py
gooddata_sdk/catalog/data_source/declarative_model/physical_model/__init__.py
gooddata_sdk/catalog/data_source/declarative_model/physical_model/column.py
gooddata_sdk/catalog/data_source/declarative_model/physical_model/pdm.py
gooddata_sdk/catalog/data_source/declarative_model/physical_model/table.py
gooddata_sdk/catalog/data_source/entity_model/__init__.py
gooddata_sdk/catalog/data_source/entity_model/data_source.py
gooddata_sdk/catalog/data_source/entity_model/content_objects/__init__.py
gooddata_sdk/catalog/data_source/validation/__init__.py
gooddata_sdk-1.58.0.dist-info/METADATA
gooddata_sdk-1.58.0.dist-info/WHEEL
gooddata_sdk-1.58.0.dist-info/entry_points.txt
gooddata_sdk-1.58.0.dist-info/licenses/LICENSE.txt
gooddata_sdk-1.58.0.dist-info/RECORD
