Metadata-Version: 2.4
Name: gooddata-sdk
Version: 1.58.0
Summary: GoodData Cloud Python SDK
Project-URL: Documentation, https://www.gooddata.com/docs/python-sdk/1.58.0
Project-URL: Source, https://github.com/gooddata/gooddata-python-sdk
Author-email: GoodData <support@gooddata.com>
License-Expression: MIT
License-File: LICENSE.txt
Keywords: analytics,api,business,cloud,gooddata,headless,headless-bi,intelligence,layer,metrics,native,sdk,semantic,sql
Classifier: Development Status :: 5 - Production/Stable
Classifier: Environment :: Console
Classifier: Programming Language :: Python :: 3.10
Classifier: Programming Language :: Python :: 3.11
Classifier: Programming Language :: Python :: 3.12
Classifier: Programming Language :: Python :: 3.13
Classifier: Programming Language :: Python :: 3.14
Classifier: Topic :: Database
Classifier: Topic :: Scientific/Engineering
Classifier: Topic :: Software Development
Classifier: Typing :: Typed
Requires-Python: <4.0,>=3.10
Requires-Dist: attrs<=24.2.0,>=21.4.0
Requires-Dist: brotli==1.2.0
Requires-Dist: cattrs<=24.1.1,>=22.1.0
Requires-Dist: gooddata-api-client~=1.58.0
Requires-Dist: python-dateutil>=2.5.3
Requires-Dist: python-dotenv<2.0.0,>=1.0.0
Requires-Dist: pyyaml>=6.0
Requires-Dist: requests~=2.32.0
